{"seq_groups": 1, "events": [{"frame": "0", "seq": "0", "file": "common/npc_step1.wav"}, {"frame": "0", "seq": "0", "file": "common/npc_step3.wav"}, {"frame": "0", "seq": "1", "file": "common/npc_step1.wav"}, {"frame": "8", "seq": "1", "file": "common/npc_step3.wav"}, {"frame": "0", "seq": "2", "file": "common/npc_step2.wav"}, {"frame": "9", "seq": "2", "file": "common/npc_step4.wav"}, {"frame": "0", "seq": "3", "file": "common/npc_step2.wav"}, {"frame": "9", "seq": "3", "file": "common/npc_step4.wav"}, {"frame": "0", "seq": "4", "file": "common/npc_step2.wav"}, {"frame": "9", "seq": "4", "file": "common/npc_step4.wav"}], "tri_count": "1062", "hash": "d5a82b7e59d529f38c99407e3917abb9"}